[
 {
  "customer_escalate_to": "r6ig51v9f3",
  "customer_party_name": null,
  "docstatus": 0,
  "doctype": "Risk Levels Child",
  "modified": "2024-12-22 11:33:01.708878",
  "name": "brjk8h6anp",
  "parent": "PC-2024-022",
  "parentfield": "risk_levels",
  "parenttype": "Project Charter",
  "resolve_time_hours": 24.0,
  "response_time_hours": 4.0,
  "risk_description": "Significant impact; major service disruption requiring immediate attention.",
  "risk_level": "r7gu2bucs0",
  "service_provider_escalate_to": "r7bqpfdu2d",
  "service_provider_party_name": null
 },
 {
  "customer_escalate_to": "qut2s9qias",
  "customer_party_name": null,
  "docstatus": 0,
  "doctype": "Risk Levels Child",
  "modified": "2024-12-22 11:33:01.708878",
  "name": "brjkdedh22",
  "parent": "PC-2024-022",
  "parentfield": "risk_levels",
  "parenttype": "Project Charter",
  "resolve_time_hours": 72.0,
  "response_time_hours": 24.0,
  "risk_description": "Minimal impact; does not disrupt services significantly.",
  "risk_level": "r0tklcrcl7",
  "service_provider_escalate_to": "r0m321cf1r",
  "service_provider_party_name": null
 },
 {
  "customer_escalate_to": "r4ulgg5gdq",
  "customer_party_name": null,
  "docstatus": 0,
  "doctype": "Risk Levels Child",
  "modified": "2024-12-22 11:33:01.708878",
  "name": "brjkr05h9c",
  "parent": "PC-2024-022",
  "parentfield": "risk_levels",
  "parenttype": "Project Charter",
  "resolve_time_hours": 48.0,
  "response_time_hours": 12.0,
  "risk_description": "Moderate impact; minor service disruption, but workaround available.",
  "risk_level": "r5phr75mr1",
  "service_provider_escalate_to": "r5hdhgp6tv",
  "service_provider_party_name": null
 },
 {
  "customer_escalate_to": "r8i0tbdr2q",
  "customer_party_name": null,
  "docstatus": 0,
  "doctype": "Risk Levels Child",
  "modified": "2024-12-22 11:33:01.708878",
  "name": "brjkt7243t",
  "parent": "PC-2024-022",
  "parentfield": "risk_levels",
  "parenttype": "Project Charter",
  "resolve_time_hours": 4.0,
  "response_time_hours": 1.0,
  "risk_description": "Severe impact; complete service failure or security breach.",
  "risk_level": "ra4gojjimk",
  "service_provider_escalate_to": "ra0jp7aat9",
  "service_provider_party_name": null
 }
]